[
  {
    "symbol": "0GUSDT",
    "lastPrice": "0.5697",
    "indexPrice": "0.5702",
    "markPrice": "0.5697",
    "prevPrice24h": "0.5809",
    "price24hPcnt": "-0.01928",
    "highPrice24h": "0.5881",
    "lowPrice24h": "0.5651",
    "prevPrice1h": "0.5684",
    "openInterest": "6784988.6",
    "openInterestValue": "3865408.01",
    "turnover24h": "905212.2038",
    "volume24h": "1573991.6000",
    "fundingRate": "0.00005",
    "nextFundingTime": "1773590400000",
    "predictedDeliveryPrice": "",
    "basisRate": "",
    "deliveryFeeRate": "",
    "deliveryTime": "0",
    "ask1Size": "391.8",
    "bid1Price": "0.5695",
    "ask1Price": "0.5696",
    "bid1Size": "330.7",
    "basis": "",
    "preOpenPrice": "",
    "preQty": "",
    "curPreListingPhase": "Finished",
    "fundingIntervalHour": "4",
    "basisRateYear": "",
    "fundingCap": "0.01"
  },
  {
    "symbol": "1000000BABYDOGEUSDT",
    "lastPrice": "0.0004390",
    "indexPrice": "0.0004391",
    "markPrice": "0.0004390",
    "prevPrice24h": "0.0004094",
    "price24hPcnt": "0.0723",
    "highPrice24h": "0.0004650",
    "lowPrice24h": "0.0004074",
    "prevPrice1h": "0.0004371",
    "openInterest": "1454977600",
    "openInterestValue": "638735.17",
    "turnover24h": "762787.2701",
    "volume24h": "1751587700.0000",
    "fundingRate": "0.00005",
    "nextFundingTime": "1773590400000",
    "predictedDeliveryPrice": "",
    "basisRate": "",
    "deliveryFeeRate": "",
    "deliveryTime": "0",
    "ask1Size": "187500",
    "bid1Price": "0.0004390",
    "ask1Price": "0.0004393",
    "bid1Size": "219200",
    "basis": "",
    "preOpenPrice": "",
    "preQty": "",
    "curPreListingPhase": "",
    "fundingIntervalHour": "4",
    "basisRateYear": "",
    "fundingCap": "0.02"
  }
]